.flake8
.git_archival.txt
.gitattributes
.gitignore
.pre-commit-config.yaml
AUTHORS.md
CHANGELOG.md
CONTRIBUTING.rst
LICENSE
LICENSE_rioxarray
MANIFEST.in
README.rst
RELEASING.md
pyproject.toml
requirements-dev.txt
requirements.txt
setup.py
.github/dependabot.yml
.github/workflows/ci.yaml
.github/workflows/deploy-sdist.yaml
continuous_integration/environment.yaml
docs/Makefile
docs/_config.yml
docs/make.bat
docs/source/conf.py
docs/source/contributing.rst
docs/source/faq.rst
docs/source/index.rst
docs/source/installation.rst
docs/source/related.rst
docs/source/roadmap.rst
docs/source/_static/.placeholder
docs/source/howtos/access_crs.rst
docs/source/howtos/coordinates.rst
docs/source/howtos/index.rst
docs/source/howtos/set_dims.rst
docs/source/howtos/write_crs.rst
docs/source/howtos/write_gcps.rst
docs/source/topics/coordinates.rst
docs/source/topics/dimensions.rst
docs/source/topics/projections.rst
docs/source/topics/xarray_accessors.rst
docs/source/tutorials/index.rst
geoxarray/__init__.py
geoxarray/accessor.py
geoxarray/coords.py
geoxarray/version.py
geoxarray.egg-info/PKG-INFO
geoxarray.egg-info/SOURCES.txt
geoxarray.egg-info/dependency_links.txt
geoxarray.egg-info/requires.txt
geoxarray.egg-info/top_level.txt
geoxarray/tests/__init__.py
geoxarray/tests/conftest.py
geoxarray/tests/test_accessor/__init__.py
geoxarray/tests/test_accessor/_data_array_cases.py
geoxarray/tests/test_accessor/_dataset_cases.py
geoxarray/tests/test_accessor/_shared.py
geoxarray/tests/test_accessor/test_accessor_data_arr.py
geoxarray/tests/test_accessor/test_accessor_dataset.py