Metadata-Version: 2.1
Name: geoxarray
Version: 0.2.0
Summary: Geolocation utilities for xarray objects
Home-page: https://github.com/geoxarray/geoxarray
Author: geoxarray Developers
Author-email: 
License: Apache
Classifier: Development Status :: 2 - Pre-Alpha
Classifier: License :: OSI Approved :: Apache Software License
Classifier: Operating System :: OS Independent
Classifier: Intended Audience :: Science/Research
Classifier: Natural Language :: English
Classifier: Programming Language :: Python :: 3
Classifier: Topic :: Scientific/Engineering
Requires-Python: >=3.9
License-File: LICENSE
License-File: LICENSE_rioxarray
License-File: AUTHORS.md
Requires-Dist: xarray
Requires-Dist: pyproj>=2.2
Provides-Extra: pyresample
Requires-Dist: pyresample; extra == "pyresample"
Provides-Extra: docs
Requires-Dist: sphinx_rtd_theme; extra == "docs"
Requires-Dist: numpydoc; extra == "docs"
Requires-Dist: sphinx_copybutton; extra == "docs"
Requires-Dist: sphinxcontrib-apidoc; extra == "docs"
Requires-Dist: pyresample; extra == "docs"
Provides-Extra: all
Requires-Dist: sphinxcontrib-apidoc; extra == "all"
Requires-Dist: sphinx_copybutton; extra == "all"
Requires-Dist: pyresample; extra == "all"
Requires-Dist: numpydoc; extra == "all"
Requires-Dist: sphinx_rtd_theme; extra == "all"
